<?xml version="1.0" encoding="UTF-8"?>
<root><title>Письменный памятник (стела) Талас IV</title><time>VIII-X вв.</time><hronology caption="Историческая справка">VIII-X ғ</hronology><history></history><names caption="Названия памятника">«Памятники Таласского побережья», «Таласские рунические памятники», «Памятник №4»</names><place caption="Место обнаружения и фактическое местонахождение памятника">Памятник был обнаружен в Айр-Там-Ой (Кырык-Казык), в 8 км к юго-востоку от города Талас (бывший уезд Аулие-Ата, городок Дмитриевский).</place><store>Хранится в Государственном историческом музее г.Бишкек, Киргизия.</store><general caption="Краткое описание">Был найден рядом с памятниками Талас I, II, III.</general><description>Сделан из светло-серого глинистого камня. Высечена надпись из 5 строк.</description><size caption="Размеры памятника">100 х 50 см.</size><investigation caption="Исследования">Памятник был найден в 1898 г. Г.Гейкелем &lt;sup&gt;&lt;a name='source_345' class='myref' href='#label_345'&gt;345&lt;/a&gt;&lt;/sup&gt;. П.М.Мелорианский, Ю.Немет &lt;sup&gt;&lt;a name='source_346' class='myref' href='#label_346'&gt;346&lt;/a&gt;&lt;/sup&gt;, С.Е.Малов &lt;sup&gt;&lt;a name='source_347' class='myref' href='#label_347'&gt;347&lt;/a&gt;&lt;/sup&gt;, Х.Н.Орхун &lt;sup&gt;&lt;a name='source_348' class='myref' href='#label_348'&gt;348&lt;/a&gt;&lt;/sup&gt;, И.А.Батманов &lt;sup&gt;&lt;a name='source_349' class='myref' href='#label_349'&gt;349&lt;/a&gt;&lt;/sup&gt; , Ч.Жумагулов &lt;sup&gt;&lt;a name='source_350' class='myref' href='#label_350'&gt;350&lt;/a&gt;&lt;/sup&gt;, А.С.Аманжолов &lt;sup&gt;&lt;a name='source_351' class='myref' href='#label_351'&gt;351&lt;/a&gt;&lt;/sup&gt; вели исследования.</investigation><details caption="Дополнительная информация">Н.Базылхан "Көне түрік бітіктастары мен ескерткіштері (Орхон, Ениесей, Талас)" //"Қазақстан тарихы түркі тілді деректемелерде" атты сериясы бойынша. II том. - Алматы: Дайк-пресс, 2005. - Б.221-222.</details><pdfs caption="Полнотекстовая информация"/><refs><ref nm="345">Heikel H.T. Аltertümer aus dem Tale des Talas in Turkestan . Travaux ethnographiques, 1918, VII. Taf. XXII-XXIV.</ref><ref nm="346">Nemet Julius Die Köktürkischen Grabinschriften aus dem Tale des Talas in Turkestan // Körösi Csoma –Archivium . Edited by Gyula Nemeth. volume II, Budapest 1926-1932. authorized print by E.I. Brill, Leiden, 1967. pp. 140-141.</ref><ref nm="347">Малов С.Е.Таласский памятник // Памятники древнетюркской письменности .Тексты и исследования. М.-Л., 1951, С.74-75. С.Е.Маловтың транскрипциясы мен орысша аудармасы: &#13;
Atï čur(a) otuz oγlan asyγ ačyγ adyrylmyš &#13;
size talčyγ eren size oγlan čur ulaju qalmyš qatuny tuly qalmyš&#13;
«Имя его- Чур. От вас тридцать огланов от выгод и благ (мира) он отделился (т.е. умер) .Вам доверенные мужи Оглан –Чур, наследуя остался. Жена его вдовой остались».</ref><ref nm="348">Orkun H.N. Talas yazitlari // Eski Türk yazîtlari. Istanbul, 1936. T-II. 136 s.</ref><ref nm="349">Батманов И.А.Текст № 4 // Таласские памятники древнетюркской письменности. Фрунзе, 1971. С.14., Рис-6. И.А.Батмановтың транскрипциясы мен орысша аудармасы: &#13;
1.	Atï čur(a) otuz&#13;
2.	oγ-&#13;
3.	-lan asyγ ačyγ adyr-&#13;
4.	ylmyš size &#13;
5.	talčyγ eren size oγlan čur ulaju &#13;
6.	qalmyš &#13;
7.	qatuny tuly qalmyš&#13;
«Имя его- Чур. От вас тридцать витязей, от выгод и благ он отделился. Вам доверенные мужи витязь чур наследуя остался. Жена его сделала тул (вдовой остались)».&#13;
</ref><ref nm="350">Джумагулов Ч.По поводу одного памятника древнетюркской эпиграфики // Известия АН Киргизской ССР.1984, № 6, С.52-58. Рис.1-,2. ; Джумагулов Ч.Четвертый Таласский памятник // Эпиграфика Киргизии. Фрунзе, 1987, С.21-26. Рис.1,2. &#13;
	Мәтін жайында Ч.Жұмағұловтың транскрипциясы мен орысша аудармасы: &#13;
	1. Atï čora otuz oγlan sïγčïγ adïrïlmï (šа) sïz(a) &#13;
	2...lïγ eren sïza oγlančor ulaju qalmï [š] ...&#13;
	3...qalmïš ...&#13;
(1) Имя его- Чора. Тридцать огланов (сыновья ?) (или племя отуз оглан), защитники остались (букв.расстались) &#13;
(2) Вас храбрый сын Чор, наследуя остался &#13;
(3) ...осталися...</ref><ref nm="351">Аманжолов А.С.Т-4 (Айртам-Ой) Руническая надпись на валуне, находка 1898 г. // История и теория древнетюркского письма. Алматы, 2003. С.90. А.С.Аманжоловтың транскрипциясы мен орысша аудармасы: &#13;
		1. Atï čur(a) otuz oγlan asïγ ačï γ adïrïlmïš(а) еsiz(e) &#13;
2. [talčïγ] eren esiz(e) oγlan čur ulaju qalmïš [qatuny tulï] qalmïš(a)&#13;
1. Имя его- Чур. Увы, он етделился от тридцати огланов, от выгод и благ! &#13;
2. Увы (доверенный) муж ! (Сын) Оглан –Чур, наследуя остался. [Госпожа его вдовой] остались.</ref></refs></root>
