<?xml version="1.0" encoding="UTF-8"?>
<root><title>Древнетюркская надпись на китайской медной монете (е-78)</title><time>713-742 гг.</time><hronology caption="Историческая справка">713-742 жылдары</hronology><history></history><names caption="Названия памятника">«М1», «Е-78», «Монета с древнетюркской надписью»	  &#13;
</names><place caption="Место обнаружения и фактическое местонахождение памятника">Монета найдена в Минусинском бассейне.	 &#13;
</place><store>Хранится в музее г.Минусинск. МКМА №9905-5.	 &#13;
</store><general caption="Краткое описание">Монета «Кай юань Тун-бао» использовалась во времена династии Тан. Такими же монетами пользовались тюрки и согдийцы.	 </general><description>В середине монеты четырехугольное отверстие. На лицевой стороне четыре китайских иероглифа, на обороте выцарапаны древнетюркская надпись из 9 символов.	 </description><size caption="Размеры памятника">Длина окружности – 2,5 см.	 &#13;
</size><investigation caption="Исследования">Текст исследовали Е.Дроун &lt;sup&gt;&lt;a name='source_309' class='myref' href='#label_309'&gt;309&lt;/a&gt;&lt;/sup&gt;, В.В.Радлов &lt;sup&gt;&lt;a name='source_310' class='myref' href='#label_310'&gt;310&lt;/a&gt;&lt;/sup&gt;, Х.Н.Орхун &lt;sup&gt;&lt;a name='source_311' class='myref' href='#label_311'&gt;311&lt;/a&gt;&lt;/sup&gt;, Э.Р.Рыгдылон &lt;sup&gt;&lt;a name='source_312' class='myref' href='#label_312'&gt;312&lt;/a&gt;&lt;/sup&gt;, Д.Д.Васильев &lt;sup&gt;&lt;a name='source_313' class='myref' href='#label_313'&gt;313&lt;/a&gt;&lt;/sup&gt;, А.М.Щербак &lt;sup&gt;&lt;a name='source_314' class='myref' href='#label_314'&gt;314&lt;/a&gt;&lt;/sup&gt;, И.Г.Добродомов &lt;sup&gt;&lt;a name='source_315' class='myref' href='#label_315'&gt;315&lt;/a&gt;&lt;/sup&gt;, И.Л.Кызласов &lt;sup&gt;&lt;a name='source_316' class='myref' href='#label_316'&gt;316&lt;/a&gt;&lt;/sup&gt;.	 &#13;
</investigation><details caption="Дополнительная информация">Н.Базылхан "Көне түрік бітіктастары мен ескерткіштері (Орхон, Ениесей, Талас)" //"Қазақстан тарихы түркі тілді деректемелерде" атты сериясы бойынша. II том. - Алматы: Дайк-пресс, 2005. - Б.212.</details><pdfs caption="Полнотекстовая информация"><pdf f_author="Васильев Д.Д" f_title="Памятники тюркской рунической письменности азиатского ареала." f_in="Советская тюркология, 1976. – № 1. – С.71-81." f_name="Vasilev_1976.pdf"/></pdfs><refs><ref nm="309">Droun E. La monnaie bilingue Minoussinsk // Bulletin de Numismatique, vol.I., Paris, 1891-1892. pp. 133-135.</ref><ref nm="310">Radloff W. Inschriften auf verschiedenen aus Metall gefertigten Altarthümern . c/ Die inschrift auf einer chinesischen Münze des Minussinsk Museums // Die Alttürkischen Inscrihpiften de Mongolei. Dritte Lieferung Die Denkmäler von Koscho-Zaidam, die ubrigen denkmaler des Orchon bechens und denkmaler im flussgebiete des Jenissei. St.Petersburg, 1895. p. 346. В.В.Радловтың тиындағы түрік мәтіннің немісше аудармасы: «Beng-tschajang, eine Münze».</ref><ref nm="311">Orkun H.N. Iki ayna yaziti // Eski Türk yazîtlari. Istanbul, 1936. t-II. 170 s.</ref><ref nm="312">Рыгдылон Э.Р.Новые рунические надписи Минусинского края // Эпиграфика Востока. 1951, № 4, С.92. рис. 7, 8. Зерттеушінің ұсынған транскрипциясы: «ba aqča baln č jaiaš ?».</ref><ref nm="313">Васильев Д.Д.Монета с древнетюркскими надписями // Корпус тюркской рунической памятников бассейна Енисея. Л., 1983, С.39, 73, 115. Д.Д.Васильевтің транслитерациясы: «b ŋ č k l q č a». </ref><ref nm="314">Щербак А.М.Еще раз о монетах с руническими надписями из Минусинска // Вестник древней истории . М., 1960, №2, С.141. А.М.Щербактың аудармасы: «бің чығым ақча- 1000 расходных денежных единиц», «бір чығым ақча- одна расходная денежная единиц».</ref><ref nm="315">Добродомов И.Г.Вторичные рунические надписи на монетах и вопросы денежного обращения у древних енисейских тюрков // Ближний и средний Восток товарно-денежные отношения при феодализме. М., 1980, С.94-97. Оның болжауынша аталмыш тиындағы түрік бітік мәтіні: «Биң чикил абақыча – Тысячи чикилей (чигилей). Оберег» (Мың чігіл. Кие тұмар»).</ref><ref nm="316">Кызласов И.Л.Монеты с тюркоязычными Енисейскими надписями (К вопросу о денежном обращении в древнехакасском государсвте) // Нумизматика и эпиграфика. 1984, № XIV, С.84-99. ; Кызласов И.Л.Рунические письменности Евразийских степей . М., 1994. С.200.</ref></refs></root>
