<?xml version="1.0" encoding="UTF-8"?>
<root><title>75 Bar-Burgazy III</title><time>VIII-X AD</time><hronology caption="Historical definition"></hronology><history></history><names caption="Names">Бар-Бургазы III; Барбургазы II, к.9 </names><place caption="Places">The text on a belt cap found in medieval burial barrow 9, sepulcher Bar-Burgazy III.</place><store>Stored in Institute of Archeology and Ethnography of Siberian Branch of Academy of Science (ИАЭ СО РАН) in Novosibirsk.</store><general caption="Specification">4 таңбадан тұратын мәтін. Новосибирск қаласында (ИАЭ СО РАН) сақтаулы.</general><description>The text of 4 characters. </description><size caption="Size"></size><investigation caption="Researches">The belt cap found during excavation held by V.Kubarev in 1979  &lt;sup&gt;&lt;a name='source_569' class='myref' href='#label_569'&gt;569&lt;/a&gt;&lt;/sup&gt;. G.Kubarev named it as Barburgazy II, k.9. &lt;sup&gt;&lt;a name='source_593' class='myref' href='#label_593'&gt;593&lt;/a&gt;&lt;/sup&gt; Kyzlasov studied the text  &lt;sup&gt;&lt;a name='source_570' class='myref' href='#label_570'&gt;570&lt;/a&gt;&lt;/sup&gt;. Publication: Kocheev &lt;sup&gt;&lt;a name='source_523' class='myref' href='#label_523'&gt;523&lt;/a&gt;&lt;/sup&gt;.</investigation><details caption="Additional information"></details><pdfs caption="Full-text information"><pdf f_author="Кочеев В.А" f_title="Свод древнетюркских рунических памятников Горного Алтая. Горно-Алтайск: АКИН, 2006. – 52 с." f_in="" f_name="kocheev_altai.pdf"/></pdfs><refs><ref nm="569">Кызласов И.Л. Памятники рунической письменности Горного Алтая. Часть 1. Памятники енисейского письма. - Горно-Алтайск, 2002. - С. 45-48.</ref><ref nm="593">Кормушин И.В.Тюркские Енисейские эпитафии. Тексты и исследования. М., 1997.</ref><ref nm="570">Кубарев Г.В. Новая руническая надпись с Алтая // Проблемы археологии, этнографии, антропологии Сибири и сопредельных территорий. - Новосибирск, 1997. - Т. III. - С. 209-212. -Рис. 1, 2.</ref><ref nm="523">Кызласов И.Л. Рунические письменности евразийских степей.-М. 1994.-С. 318.-Рис. 18.</ref></refs></root>
