<?xml version="1.0" encoding="UTF-8"?>
<root><title>Or. 8212 (104)</title><time></time><hronology caption="Historical definition"></hronology><history></history><names caption="Names">British Library (Stein Collections) Or.8212/104</names><place caption="Places">Дунхуаннан табылған.</place><store>Британ кітапханасында сақтаулы. Or. 8212 (104).</store><general caption="Specification">Ұзын қағаз орамына жазылған 466 жолдан тұратын ұйғыр тіліндегі мәтін. "Сегіз сиқырлы ғажайып" (Sakiz yukmak boguluk arvis) атты будда сутрасының ұйғыршасы. Жапон экспедициясы тапқан қытайша "Tian di ba yang zhou jing" сутрасының аудармасы деп есептеледі.  &lt;sup&gt;&lt;a name='source_589' class='myref' href='#label_589'&gt;589&lt;/a&gt;&lt;/sup&gt;</general><description>Орамның сыртқы бетінде бірнеше көне түрік бітікпен жазылған азғантай сөз бар. Ұйғырша мәтін жазылған орамның бас жағы бүлінген. </description><size caption="Size">Ені - 27 см, ұзындығы - 790.5 см. </size><investigation caption="Researches"></investigation><details caption="Additional information"></details><pdfs caption="Full-text information"/><refs><ref nm="589">Zwalf W. Buddhism, Art and Faith. London: British Museum, 1985. </ref></refs></root>
