<?xml version="1.0" encoding="UTF-8"?>
<root tid="4" oid="160" kz="OR.8212 (76) түрік бітік мәтіні" ru="Древнетюркская надпись OR.8212 (76)" en="OR.8212 (76) түрік бітік мәтіні"><page pid="1" title_kz="" title_en="" title_ru=""><line f_line="1" or="turtiW JTUxUz UTUz Q" tr="törtinči : ay toquz : otuz : Q-" kz="" ru="" en=""/><line f_line="2" or="UNGNCUR JRiki URyU TUD" tr="unïγïn Čor : yarïqï : oruŋu : Tud-" kz="" ru="" en=""/><line f_line="3" or="N Cigsi Ka JRLG BULTi" tr="ïn : Čigsi : ke : yarlïγ : boltï" kz="" ru="" en=""/><line f_line="4" or="LNi iCiGaKiJRJki CiK " tr="alïnï : ičireki eki yaryaqï : Čik :" kz="" ru="" en=""/><line f_line="5" or="bilga CigsiKa JRLG BULTi" tr="Bilge : Čigsike : yarlïγ : boltï" kz="" ru="" en=""/><line f_line="6" or="UTQa Kunmis QiLiCuziKa" tr="otqa : kunmis : Qïlïč Üzike " kz="" ru="" en=""/><line f_line="7" or="JRLG BULTi Kulug URyU" tr="yarlïγ : boltï : Külüg : oruŋu" kz="" ru="" en=""/><line f_line="8" or="Qa TiG JRLG BULTi Kupa" tr="qa : Atïγ : yarlïγ : boltï : Ekü apa" kz="" ru="" en=""/><line f_line="9" or="JRik" tr="yarïq" kz="" ru="" en=""/><line f_line="10" or="JRik uCun jir JRik JR" tr="yarïq : üčün : Yir : yarïq : yar-" kz="" ru="" en=""/><line f_line="11" or="LG BULTi LNJiCGiKimud" tr="lïγ : boltï : Alan ayïčïγï kemüd" kz="" ru="" en=""/><line f_line="12" or="KlurmisuC JRikDugaKa" tr="kelürmis üč : yarïqdï ügeke" kz="" ru="" en=""/><line f_line="13" or="bir JRLG BULTi Kdim URyU" tr="bir : yarlïγ : boltï : Kedim : oruŋu" kz="" ru="" en=""/><line f_line="14" or="Qa...d...uryUJRiGaKa ..." tr="qa ... d ... üriŋ Yoriγa ke : ..." kz="" ru="" en=""/><line f_line="15" or="SUGCUBLik Da Kirmis JRi" tr="Soγïčï balïq : da : eki ermis : yari-" kz="" ru="" en=""/><line f_line="16" or="k Da BJirQULRQa LTi JRik" tr="q : da : Bay ir qularqa : altï : yarïq" kz="" ru="" en=""/><line f_line="17" or="tiginKa BRGLNSyUN Qa..." tr="tiginke : Barïγlan Saŋun ..." kz="" ru="" en=""/><line f_line="18" or="QUTUz URyUQa KuC Cigsi ..." tr="q otuz : oruŋuqa : Kuč : Čigsi ..." kz="" ru="" en=""/><line f_line="19" or="...siya ...RGCiRQa s Knsig Q" tr="... siηe : ... Arïγčï Arqa : si : Kensig : q-" kz="" ru="" en=""/><line f_line="20" or="a trligpa Qa QUTLUG Qa ..." tr="a : Terlig apa : qa : Qutluγ : qa : ..." kz="" ru="" en=""/><line f_line="21" or="...rKa URyU SyUN Qa" tr="... erke : oruŋu : Saŋun : qa" kz="" ru="" en=""/><line f_line="22" or="TCapa iCraKiKa bir JRik JU" tr="Tač apa ičirekike bir : yarïq : yo" kz="" ru="" en=""/><line f_line="23" or="RUk birla" tr="ruq : birle" kz="" ru="" en=""/></page><page pid="2" title_kz="" title_en="" title_ru=""><line f_line="1" or="BUCURQa JRik" tr="Bučurqa : yorïq :" kz="" ru="" en=""/><line f_line="2" or="bir uKsKa bir JRik BwDi " tr="bir : ükiske : bir : yorïq : boltï :" kz="" ru="" en=""/><line f_line="3" or="tmzma Ka JRik QUJGU Qa bir" tr="Temizime : ke : yorïq : Quyγu : qa : bir" kz="" ru="" en=""/><line f_line="4" or="JRik QULapaURyUQa JRik..." tr="yorïq : Qul apa orïηuqa : yorïq : ..." kz="" ru="" en=""/><line f_line="5" or="QUFCi lrKa ... JRik TJ..." tr="qoňčï : Elirke ... yorïq : tay.." kz="" ru="" en=""/><line f_line="6" or="bir KuKuzma JRik ..." tr="bir : küküzime : yorïq ..." kz="" ru="" en=""/><line f_line="7" or="BULTi laKul..." tr="boltï : Ele kul..." kz="" ru="" en=""/><line f_line="8" or="k Kna BU ..." tr="q : Kene : bu..." kz="" ru="" en=""/><line f_line="9" or="ur..." tr="ür..." kz="" ru="" en=""/></page><refs/></root>
